SpringFramework5ZhongwenWendang/README.md
SpringFramework5ZhongwenWendang/__init__.py
SpringFramework5ZhongwenWendang/__main__.py
SpringFramework5ZhongwenWendang/file.epub
SpringFramework5ZhongwenWendang/index.html
SpringFramework5ZhongwenWendang/css/__init__.py
SpringFramework5ZhongwenWendang/css/annotations.css
SpringFramework5ZhongwenWendang/css/main.css
SpringFramework5ZhongwenWendang/css/normalize.css
SpringFramework5ZhongwenWendang/css/popup.css
SpringFramework5ZhongwenWendang/font/__init__.py
SpringFramework5ZhongwenWendang/font/fontello.eot
SpringFramework5ZhongwenWendang/font/fontello.svg
SpringFramework5ZhongwenWendang/font/fontello.ttf
SpringFramework5ZhongwenWendang/font/fontello.woff
SpringFramework5ZhongwenWendang/img/__init__.py
SpringFramework5ZhongwenWendang/img/annotator-glyph-sprite.png
SpringFramework5ZhongwenWendang/img/annotator-icon-sprite.png
SpringFramework5ZhongwenWendang/img/apple-touch-icon.png
SpringFramework5ZhongwenWendang/img/cancelfullscreen.png
SpringFramework5ZhongwenWendang/img/close.png
SpringFramework5ZhongwenWendang/img/fullscreen.png
SpringFramework5ZhongwenWendang/img/loader.gif
SpringFramework5ZhongwenWendang/img/menu-icon.png
SpringFramework5ZhongwenWendang/img/save.png
SpringFramework5ZhongwenWendang/img/saved.png
SpringFramework5ZhongwenWendang/img/settings-s.png
SpringFramework5ZhongwenWendang/img/settings.png
SpringFramework5ZhongwenWendang/img/star.png
SpringFramework5ZhongwenWendang/js/__init__.py
SpringFramework5ZhongwenWendang/js/epub.js
SpringFramework5ZhongwenWendang/js/epub.min.js
SpringFramework5ZhongwenWendang/js/epub.min.map
SpringFramework5ZhongwenWendang/js/hooks.min.js
SpringFramework5ZhongwenWendang/js/hooks.min.map
SpringFramework5ZhongwenWendang/js/reader.js
SpringFramework5ZhongwenWendang/js/reader.js.map
SpringFramework5ZhongwenWendang/js/reader.min.js
SpringFramework5ZhongwenWendang/js/reader.min.map
SpringFramework5ZhongwenWendang/js/hooks/__init__.py
spring_framework_5_zhongwen_wendang-2024.3.4.0.dist-info/METADATA
spring_framework_5_zhongwen_wendang-2024.3.4.0.dist-info/WHEEL
spring_framework_5_zhongwen_wendang-2024.3.4.0.dist-info/entry_points.txt
spring_framework_5_zhongwen_wendang-2024.3.4.0.dist-info/top_level.txt
spring_framework_5_zhongwen_wendang-2024.3.4.0.dist-info/RECORD
